notebooksend/__init__.py
notebooksend/_version.py
notebooksend-4.0.4.data/data/share/jupyter/labextensions/notebooksend/package.json
notebooksend-4.0.4.data/data/share/jupyter/labextensions/notebooksend/schemas/notebooksend/dialogShownSettings.json
notebooksend-4.0.4.data/data/share/jupyter/labextensions/notebooksend/schemas/notebooksend/package.json.orig
notebooksend-4.0.4.data/data/share/jupyter/labextensions/notebooksend/schemas/notebooksend/settings.json
notebooksend-4.0.4.data/data/share/jupyter/labextensions/notebooksend/static/354.7cbe78785d617175cc1e.js
notebooksend-4.0.4.data/data/share/jupyter/labextensions/notebooksend/static/354.7cbe78785d617175cc1e.js.LICENSE.txt
notebooksend-4.0.4.data/data/share/jupyter/labextensions/notebooksend/static/480.04a54835dcf969e50f32.js
notebooksend-4.0.4.data/data/share/jupyter/labextensions/notebooksend/static/747.007f07e4520b1e018291.js
notebooksend-4.0.4.data/data/share/jupyter/labextensions/notebooksend/static/924.372330dfb5635967845e.js
notebooksend-4.0.4.data/data/share/jupyter/labextensions/notebooksend/static/remoteEntry.eac9073326c6dc5d482a.js
notebooksend-4.0.4.data/data/share/jupyter/labextensions/notebooksend/static/style.js
notebooksend-4.0.4.data/data/share/jupyter/labextensions/notebooksend/static/third-party-licenses.json
notebooksend-4.0.4.data/data/share/jupyter/labextensions/notebooksend/install.json
notebooksend-4.0.4.dist-info/METADATA
notebooksend-4.0.4.dist-info/WHEEL
notebooksend-4.0.4.dist-info/licenses/LICENSE
notebooksend-4.0.4.dist-info/RECORD
