Metadata-Version: 2.1
Name: notebooksend
Version: 4.0.4
Summary: A JupyterLab extension to send notebook execution and activity to a self-hosted backend.
Project-URL: Homepage, https://github.com/chili-epfl/jupyter-dashboard-send-extension
Project-URL: Bug Tracker, https://github.com/chili-epfl/jupyter-dashboard-send-extension/issues
Project-URL: Repository, https://github.com/chili-epfl/jupyter-dashboard-send-extension.git
Author-email: Raphael Marietan <me@test.com>
License: BSD 3-Clause License
License-File: LICENSE
Classifier: Framework :: Jupyter
Classifier: Framework :: Jupyter :: JupyterLab
Classifier: Framework :: Jupyter :: JupyterLab :: 4
Classifier: Framework :: Jupyter :: JupyterLab :: Extensions
Classifier: Framework :: Jupyter :: JupyterLab :: Extensions :: Prebuilt
Classifier: License :: OSI Approved :: BSD License
Classifier: Programming Language :: Python
Classifier: Programming Language :: Python :: 3
Classifier: Programming Language :: Python :: 3.8
Classifier: Programming Language :: Python :: 3.9
Classifier: Programming Language :: Python :: 3.10
Classifier: Programming Language :: Python :: 3.11
Requires-Python: >=3.8
